first_package_andrey_vorobyov/__init__.py
first_package_andrey_vorobyov/example.py
first_package_andrey_vorobyov-0.0.3.dist-info/LICENSE
first_package_andrey_vorobyov-0.0.3.dist-info/METADATA
first_package_andrey_vorobyov-0.0.3.dist-info/WHEEL
first_package_andrey_vorobyov-0.0.3.dist-info/top_level.txt
first_package_andrey_vorobyov-0.0.3.dist-info/RECORD
