Metadata-Version: 2.1
Name: first-package-andrey-vorobyov
Version: 0.0.3
Summary: my first package
Author: Andrey Vorobyov
Author-email: andrey.vorobyov@mail.com
License: MIT
Classifier: Programming Language :: Python :: 3
Classifier: License :: OSI Approved :: MIT License
Classifier: Operating System :: OS Independent
Requires-Python: >=3.10
License-File: LICENSE
